parquery/__init__.py
parquery/aggregate.py
parquery/tool.py
parquery/transport.py
parquery/write.py
parquery/tests/__init__.py
parquery/tests/test_parquery.py
parquery-0.1.15.dist-info/LICENSE
parquery-0.1.15.dist-info/METADATA
parquery-0.1.15.dist-info/WHEEL
parquery-0.1.15.dist-info/top_level.txt
parquery-0.1.15.dist-info/zip-safe
parquery-0.1.15.dist-info/RECORD
